[
    {
        "name": "hi",
        "urlImg": "https://picsum.photos/id/602/300/300?grayscale",
        "size": "5372",
        "modified": "25.10.2018"
    },
    {
        "name": "ocean",
        "urlImg": "https://picsum.photos/id/603/300/300?grayscale",
        "size": "5172",
        "modified": "26.10.2018"
    },
    {
        "name": "shoose",
        "urlImg": "https://picsum.photos/id/604/300/300?grayscale",
        "size": "4372",
        "modified": "27.10.2018"
    },
    {
        "name": "car",
        "urlImg": "https://picsum.photos/id/605/300/300?grayscale",
        "size": "5382",
        "modified": "28.10.2018"
    },
    {
        "name": "beech",
        "urlImg": "https://picsum.photos/id/606/300/300?grayscale",
        "size": "5392",
        "modified": "25.10.2018"
    },
    {
        "name": "fisher",
        "urlImg": "https://picsum.photos/id/607/300/300?grayscale",
        "size": "7372",
        "modified": "24.10.2018"
    },
    {
        "name": "wave",
        "urlImg": "https://picsum.photos/id/608/300/300?grayscale",
        "size": "5172",
        "modified": "23.10.2018"
    },
    {
        "name": "stones",
        "urlImg": "https://picsum.photos/id/609/300/300?grayscale",
        "size": "3372",
        "modified": "20.10.2018"
    },
    {
        "name": "sand",
        "urlImg": "https://picsum.photos/id/610/300/300?grayscale",
        "size": "8372",
        "modified": "21.10.2018"
    },
    {
        "name": "gulls",
        "urlImg": "https://picsum.photos/id/611/300/300?grayscale",
        "size": "5300",
        "modified": "30.10.2018"
    },
    {
        "name": "rocks",
        "urlImg": "https://picsum.photos/id/612/300/300?grayscale",
        "size": "6372",
        "modified": "25.10.2018"
    },
    {
        "name": "bridge",
        "urlImg": "https://picsum.photos/id/613/300/300?grayscale",
        "size": "3200",
        "modified": "20.10.2018"
    },
    {
        "name": "gulf",
        "urlImg": "https://picsum.photos/id/614/300/300?grayscale",
        "size": "5375",
        "modified": "29.10.2018"
    },
    {
        "name": "water",
        "urlImg": "https://picsum.photos/id/615/300/300?grayscale",
        "size": "5800",
        "modified": "20.10.2018"
    },
    {
        "name": "wall",
        "urlImg": "https://picsum.photos/id/616/300/300?grayscale",
        "size": "4333",
        "modified": "15.10.2018"
    },
    {
        "name": "ship",
        "urlImg": "https://picsum.photos/id/617/300/300?grayscale",
        "size": "5372",
        "modified": "25.10.2018"
    },
    {
        "name": "decor",
        "urlImg": "https://picsum.photos/id/618/300/300?grayscale",
        "size": "5366",
        "modified": "25.10.2018"
    },
    {
        "name": "alarm",
        "urlImg": "https://picsum.photos/id/619/300/300?grayscale",
        "size": "6666",
        "modified": "15.10.2018"
    },
    {
        "name": "bicycle",
        "urlImg": "https://picsum.photos/id/620/300/300?grayscale",
        "size": "5372",
        "modified": "25.10.2018"
    },
    {
        "name": "under brigde",
        "urlImg": "https://picsum.photos/id/621/300/300?grayscale",
        "size": "5372",
        "modified": "25.10.2018"
    },
    {
        "name": "town",
        "urlImg": "https://picsum.photos/id/622/300/300?grayscale",
        "size": "5372",
        "modified": "25.10.2018"
    }

]